<?xml version="1.0" encoding="utf-8" ?><dwsync><file name="commentView.php" server="merak.starfree.jp//gallery/" local="3710455472" remote="3710497920" Dst="-1" /><file name="contentView.php" server="merak.starfree.jp//gallery/" local="3710478223" remote="3710497920" Dst="-1" /><file name="updatePassConfView.php" server="merak.starfree.jp//gallery/" local="3710817226" remote="3710817180" Dst="-1" /><file name="search_resulteView.php" server="merak.starfree.jp//gallery/" local="3709721565" remote="3710497920" Dst="-1" /><file name="delete_accountView.php" server="merak.starfree.jp//gallery/" local="3710458673" remote="3710497920" Dst="-1" /><file name="loginView.php" server="merak.starfree.jp//gallery/" local="3710501731" remote="3710501700" Dst="-1" /><file name="logoutView.php" server="merak.starfree.jp//gallery/" local="3710458761" remote="3710497920" Dst="-1" /><file name="loginNotView.php" server="merak.starfree.jp//gallery/" local="3710458714" remote="3710497920" Dst="-1" /><file name="signupView.php" server="merak.starfree.jp//gallery/" local="3710817205" remote="3710817180" Dst="-1" /><file name="searchView.php" server="merak.starfree.jp//gallery/" local="3710458986" remote="3710497920" Dst="-1" /><file name="postView.php" server="merak.starfree.jp//gallery/" local="3710458790" remote="3710497920" Dst="-1" /><file name="updateIdView.php" server="merak.starfree.jp//gallery/" local="3710466693" remote="3710497920" Dst="-1" /><file name="_index.php" server="merak.starfree.jp//gallery/" local="3708412890" remote="3710497920" Dst="-1" /><file name="updatePassView.php" server="merak.starfree.jp//gallery/" local="3710469022" remote="3710497920" Dst="-1" /><file name="accountView.php" server="merak.starfree.jp//gallery/" local="3710458612" remote="3710497920" Dst="-1" /><file name="loginYetView.php" server="merak.starfree.jp//gallery/" local="3710475390" remote="3710497920" Dst="-1" /><file name="galleryView.php" server="merak.starfree.jp//gallery/" local="3711166419" remote="3711166500" Dst="-1" /><file name="infomationView.php" server="merak.starfree.jp//gallery/" local="3710458696" remote="3710497920" Dst="-1" /><file name="mainView.php" server="merak.starfree.jp//gallery/" local="3711192776" remote="3711192780" Dst="-1" /></dwsync>